cluwards/__init__.py
cluwards/__main__.py
cluwards-1.1.2.dist-info/METADATA
cluwards-1.1.2.dist-info/WHEEL
cluwards-1.1.2.dist-info/entry_points.txt
cluwards-1.1.2.dist-info/top_level.txt
cluwards-1.1.2.dist-info/zip-safe
cluwards-1.1.2.dist-info/RECORD
